wdcrypt/__init__.py
wdcrypt/cli.py
wdcrypt/decrypt.py
wdcrypt/encrypt.py
wdcrypt-1.9.dist-info/LICENSE
wdcrypt-1.9.dist-info/METADATA
wdcrypt-1.9.dist-info/WHEEL
wdcrypt-1.9.dist-info/entry_points.txt
wdcrypt-1.9.dist-info/top_level.txt
wdcrypt-1.9.dist-info/RECORD
